LICENSE
README.rst
setup.py
no_subclasses/__init__.py
no_subclasses/__main__.py
no_subclasses/no_subclasses.py
no_subclasses/safe_eval.py
no_subclasses.egg-info/PKG-INFO
no_subclasses.egg-info/SOURCES.txt
no_subclasses.egg-info/dependency_links.txt
no_subclasses.egg-info/requires.txt
no_subclasses.egg-info/top_level.txt