Metadata-Version: 2.1
Name: no-subclasses
Version: 1.0.2
Summary: A library that removes the __subclasses__() list from all classes.一个清除所有类的__subclasses__()列表的库。
Home-page: https://github.com/qfcy/no-subclasses
Author: qfcy
Author-email: 3076711200@qq.com
Keywords: subclasses,exec,eval,sandbox,security,environment
Classifier: Programming Language :: Python
Classifier: Topic :: Utilities
Classifier: Topic :: Security
Classifier: Topic :: Software Development :: Libraries :: Python Modules
Classifier: License :: OSI Approved :: MIT License
License-File: LICENSE
